cnq/__init__.py
cnq/configuration.ini
cnq/am/__init__.py
cnq/am/logging.ini
cnq/am/enr/__init__.py
cnq/am/enr/am.py
cnq/am/enr/main.py
cnq/am/enr/test.py
mgr_0407_o_cnq_dev-0.0.2.dist-info/METADATA
mgr_0407_o_cnq_dev-0.0.2.dist-info/WHEEL
mgr_0407_o_cnq_dev-0.0.2.dist-info/top_level.txt
mgr_0407_o_cnq_dev-0.0.2.dist-info/RECORD
