Metadata-Version: 2.1
Name: mgr-0407-o-cnq-dev
Version: 0.0.2
Summary: CNQ Test Dev machine
Home-page: https://github.com/pypa/sampleproject
Author: MGR
Author-email: mohamed.grini@aosis.net
Project-URL: Bug Tracker, https://github.com/pypa/sampleproject/issues
Classifier: Programming Language :: Python :: 3
Classifier: License :: OSI Approved :: MIT License
Classifier: Operating System :: OS Independent
Requires-Python: >=3.6
